setup.py
dm/__init__.py
dm.plonepatches.reload.egg-info/PKG-INFO
dm.plonepatches.reload.egg-info/SOURCES.txt
dm.plonepatches.reload.egg-info/dependency_links.txt
dm.plonepatches.reload.egg-info/namespace_packages.txt
dm.plonepatches.reload.egg-info/not-zip-safe
dm.plonepatches.reload.egg-info/requires.txt
dm.plonepatches.reload.egg-info/top_level.txt
dm/plonepatches/__init__.py
dm/plonepatches/reload/README.txt
dm/plonepatches/reload/VERSION.txt
dm/plonepatches/reload/__init__.py
dm/plonepatches/reload/tests/__init__.py
dm/plonepatches/reload/tests/reload_count.py
dm/plonepatches/reload/tests/reload_module.py
dm/plonepatches/reload/tests/test_reload.py