Metadata-Version: 1.1
Name: dm.plonepatches.reload
Version: 1.1
Summary: Patches for "plone.reload" improvement.
Home-page: http://pypi.python.org/pypi/dm.plonepatches.reload
Author: Dieter Maurer
Author-email: dieter@handshake.de
License: GPL
Keywords: reload development
Platform: UNKNOWN
Classifier: Development Status :: 5 - Production/Stable
Classifier: Intended Audience :: Developers
Classifier: License :: OSI Approved :: GNU General Public License (GPL)
Classifier: Framework :: Plone
Classifier: Operating System :: OS Independent
Classifier: Programming Language :: Python
Classifier: Programming Language :: Python :: 2.7
Classifier: Programming Language :: Python :: 3
Classifier: Topic :: Utilities
